eNlightSDK/__init__.py
eNlightSDK/enlight_cloud.py
eNlightSDK/classes/__init__.py
eNlightSDK/classes/caller.py
eNlightSDK/classes/set_projects.py
eNlightSDK/classes/vm.py
eNlightSDKdemo-0.1.1.dist-info/METADATA
eNlightSDKdemo-0.1.1.dist-info/WHEEL
eNlightSDKdemo-0.1.1.dist-info/top_level.txt
eNlightSDKdemo-0.1.1.dist-info/RECORD
