Metadata-Version: 2.1
Name: eNlightSDKdemo
Version: 0.1.1
Summary: VM CRUDs
Author: Akshay Ghatol
Author-email: akshay.ghatol@esds.co.in
